Workbook

Sheet Dashboard
A1: SALES PERFORMANCE & REVENUE ANALYSIS
A2: Executive dashboard | Excel 2010 compatible
A4: Total Revenue | F4: Gross Profit | K4: Total Orders | P4: Interactive Salesperson View
A5: ='KPI Summary'!B5 -> 946169.8 | F5: ='KPI Summary'!B9 -> 404799.35 | K5: ='KPI Summary'!B6 -> 779 | P5: Select salesperson: | Q5: Tina Carlton
P7: Selected Revenue | Q7: =SUMIF(Orders_Clean!$F$5:$F$783,Q5,Orders_Clean!$Q$5:$Q$783) -> 95586.719
A8: Units Sold | F8: Avg Order Value | K8: Avg Delivery Days | P8: Selected Orders | Q8: =COUNTIF(Orders_Clean!$F$5:$F$783,Dashboard!Q5) -> 112
A9: ='KPI Summary'!B7 -> 1002395 | F9: ='KPI Summary'!B11 -> 1214.5954 | K9: ='KPI Summary'!B13 -> 11.761232 | P9: Selected Units | Q9: =SUMIF(Orders_Clean!$F$5:$F$783,Q5,Orders_Clean!$M$5:$M$783) -> 2970
P10: Selected Gross Profit | Q10: =SUMIF(Orders_Clean!$F$5:$F$783,Q5,Orders_Clean!$T$5:$T$783) -> 46112.13
A13: Salesperson Analysis | H13: Category Analysis | O13: State Analysis
A14: Salesperson | B14: Orders | C14: Revenue | H14: Product Category | I14: Units Sold | J14: Revenue | O14: State | P14: Orders | Q14: Revenue
A15: =INDEX('Salesperson Analysis'!$A$5:$A$14,MATCH(1,'Salesperson Analysis'!$G$5:$G$14,0)) -> Yvette Biti | B15: =INDEX('Salesperson Analysis'!$B$5:$B$14,MATCH(1,'Salesperson Analysis'!$G$5:$G$14,0)) -> 104 | C15: =INDEX('Salesperson Analysis'!$C$5:$C$14,MATCH(1,'Salesperson Analysis'!$G$5:$G$14,0)) -> 120963.36 | H15: ='Category Analysis'!A5 -> Furniture | I15: ='Category Analysis'!B5 -> 478 | J15: ='Category Analysis'!C5 -> 24961.874 | O15: ='State Analysis'!A5 -> NSW | P15: ='State Analysis'!B5 -> 447 | Q15: ='State Analysis'!C5 -> 578438.14
A16: =INDEX('Salesperson Analysis'!$A$5:$A$14,MATCH(2,'Salesperson Analysis'!$G$5:$G$14,0)) -> Natasha Song | B16: =INDEX('Salesperson Analysis'!$B$5:$B$14,MATCH(2,'Salesperson Analysis'!$G$5:$G$14,0)) -> 52 | C16: =INDEX('Salesperson Analysis'!$C$5:$C$14,MATCH(2,'Salesperson Analysis'!$G$5:$G$14,0)) -> 105627.71 | H16: ='Category Analysis'!A6 -> Office Supplies | I16: ='Category Analysis'!B6 -> 16669 | J16: ='Category Analysis'!C6 -> 266028.18 | O16: ='State Analysis'!A6 -> VIC | P16: ='State Analysis'!B6 -> 184 | Q16: ='State Analysis'!C6 -> 210288.43
A17: =INDEX('Salesperson Analysis'!$A$5:$A$14,MATCH(3,'Salesperson Analysis'!$G$5:$G$14,0)) -> Charlie Bui | B17: =INDEX('Salesperson Analysis'!$B$5:$B$14,MATCH(3,'Salesperson Analysis'!$G$5:$G$14,0)) -> 38 | C17: =INDEX('Salesperson Analysis'!$C$5:$C$14,MATCH(3,'Salesperson Analysis'!$G$5:$G$14,0)) -> 74020.828 | H17: ='Category Analysis'!A7 -> Technology | I17: ='Category Analysis'!B7 -> 3713 | J17: ='Category Analysis'!C7 -> 655179.74 | O17: ='State Analysis'!A7 -> WA | P17: ='State Analysis'!B7 -> 148 | Q17: ='State Analysis'!C7 -> 157443.23
A18: =INDEX('Salesperson Analysis'!$A$5:$A$14,MATCH(4,'Salesperson Analysis'!$G$5:$G$14,0)) -> Mihael Khan | B18: =INDEX('Salesperson Analysis'!$B$5:$B$14,MATCH(4,'Salesperson Analysis'!$G$5:$G$14,0)) -> 55 | C18: =INDEX('Salesperson Analysis'!$C$5:$C$14,MATCH(4,'Salesperson Analysis'!$G$5:$G$14,0)) -> 76239.295
A19: =INDEX('Salesperson Analysis'!$A$5:$A$14,MATCH(5,'Salesperson Analysis'!$G$5:$G$14,0)) -> Samantha Chairs | B19: =INDEX('Salesperson Analysis'!$B$5:$B$14,MATCH(5,'Salesperson Analysis'!$G$5:$G$14,0)) -> 50 | C19: =INDEX('Salesperson Analysis'!$C$5:$C$14,MATCH(5,'Salesperson Analysis'!$G$5:$G$14,0)) -> 65786.384
A40: Monthly Revenue Analysis | H40: Customer Analysis | O40: Delivery Analysis
A41: Month | B41: Orders | C41: Revenue | H41: Customer Type | I41: Orders | J41: Revenue | O41: Month | P41: Orders | Q41: Avg Days to Deliver | R41: Revenue
A42: ='Monthly Analysis'!A5 -> Jan | B42: ='Monthly Analysis'!B5 -> 65 | C42: ='Monthly Analysis'!C5 -> 56974.562 | H42: ='Customer Analysis'!A5 -> Consumer | I42: ='Customer Analysis'!B5 -> 140 | J42: ='Customer Analysis'!C5 -> 167363.3 | O42: ='Delivery Analysis'!A5 -> Fast | P42: ='Delivery Analysis'!B5 -> 101 | Q42: ='Delivery Analysis'!C5 -> 2.0693069 | R42: ='Delivery Analysis'!D5 -> 130997.38
A43: ='Monthly Analysis'!A6 -> Feb | B43: ='Monthly Analysis'!B6 -> 53 | C43: ='Monthly Analysis'!C6 -> 58662.096 | H43: ='Customer Analysis'!A6 -> Corporate | I43: ='Customer Analysis'!B6 -> 275 | J43: ='Customer Analysis'!C6 -> 369291.8 | O43: ='Delivery Analysis'!A6 -> Standard | P43: ='Delivery Analysis'!B6 -> 137 | Q43: ='Delivery Analysis'!C6 -> 5.5985401 | R43: ='Delivery Analysis'!D6 -> 90110.98
A44: ='Monthly Analysis'!A7 -> Mar | B44: ='Monthly Analysis'!B7 -> 75 | C44: ='Monthly Analysis'!C7 -> 143970.12 | H44: ='Customer Analysis'!A7 -> Home Office | I44: ='Customer Analysis'!B7 -> 203 | J44: ='Customer Analysis'!C7 -> 220046.86 | O44: ='Delivery Analysis'!A7 -> Slow | P44: ='Delivery Analysis'!B7 -> 247 | Q44: ='Delivery Analysis'!C7 -> 10.927126 | R44: ='Delivery Analysis'!D7 -> 308364.38
A45: ='Monthly Analysis'!A8 -> Apr | B45: ='Monthly Analysis'!B8 -> 58 | C45: ='Monthly Analysis'!C8 -> 54408.572 | H45: ='Customer Analysis'!A8 -> Small Business | I45: ='Customer Analysis'!B8 -> 161 | J45: ='Customer Analysis'!C8 -> 189467.84 | O45: ='Delivery Analysis'!A8 -> Very Slow | P45: ='Delivery Analysis'!B8 -> 294 | Q45: ='Delivery Analysis'!C8 -> 18.663265 | R45: ='Delivery Analysis'!D8 -> 416697.06
A46: ='Monthly Analysis'!A9 -> May | B46: ='Monthly Analysis'!B9 -> 66 | C46: ='Monthly Analysis'!C9 -> 87835.631
A47: ='Monthly Analysis'!A10 -> Jun | B47: ='Monthly Analysis'!B10 -> 61 | C47: ='Monthly Analysis'!C10 -> 93178.52
A48: ='Monthly Analysis'!A11 -> Jul | B48: ='Monthly Analysis'!B11 -> 68 | C48: ='Monthly Analysis'!C11 -> 105093.69
A49: ='Monthly Analysis'!A12 -> Aug | B49: ='Monthly Analysis'!B12 -> 67 | C49: ='Monthly Analysis'!C12 -> 43467.029
A50: ='Monthly Analysis'!A13 -> Sep | B50: ='Monthly Analysis'!B13 -> 65 | C50: ='Monthly Analysis'!C13 -> 73635.172
A51: ='Monthly Analysis'!A14 -> Oct | B51: ='Monthly Analysis'!B14 -> 66 | C51: ='Monthly Analysis'!C14 -> 54593.492
A52: ='Monthly Analysis'!A15 -> Nov | B52: ='Monthly Analysis'!B15 -> 58 | C52: ='Monthly Analysis'!C15 -> 59446.994
A53: ='Monthly Analysis'!A16 -> Dec | B53: ='Monthly Analysis'!B16 -> 77 | C53: ='Monthly Analysis'!C16 -> 114903.93

Sheet README
A1: Sales Performance & Revenue Analysis
A2: Integrated Excel 2010 portfolio + practice workbook
A4: Project Goal | B4: Combine the skills from the three sales-analysis exercises into one realistic end-to-end reporting project.
A5: Target Roles | B5: Data Analyst | MIS Executive / MIS Analyst | Reporting Analyst
A6: Excel Version | B6: Designed for Excel 2010: SUMIF/SUMIFS, COUNTIF/COUNTIFS, AVERAGEIF, IF, TEXT, MONTH, VLOOKUP/INDEX-MATCH, Pivot-style summaries and charts.
A7: Business Questions | B7: How much revenue are we generating? Which salespeople, customers, products/categories and states drive performance? What are the monthly trends? How do discounts and delivery time affect results?
A8: Workflow | B8: Raw Orders → Cleaning/Calculated Fields → KPI & Analysis Tables → Dashboard → Practice Lab
A9: Important | B9: The three source workbooks use the same 976-order dataset with different exercises/columns. They are NOT appended together, because doing so would double/triple-count the same orders. Instead, their distinct skills are integrated into one master workbook.
A10: Master Data | B10: The Orders_Clean sheet uses the richest version of the order data and adds the useful month/profit/delivery calculations from the other exercises.
A11: Portfolio Tip | B11: For LinkedIn/GitHub, present this as one business case: 'Built an Excel 2010 sales reporting solution to analyze revenue, sales performance, customer segments, geography, product mix and delivery metrics.'

Sheet Orders_Clean
A1: Orders_Clean
A4: Order No | B4: Order Date | C4: Days to Deliver | D4: State | E4: Customer Type | F4: Salesperson | G4: Product Category | H4: Order Priority | I4: Product Name | J4: Cost Price | K4: Retail Price | L4: Profit Margin | M4: Order Quantity | N4: Sub Total | O4: Discount % | P4: Discount ₹ | Q4: Revenue | R4: Order Month | S4: Gross Cost | T4: Gross Profit | U4: Profit % | V4: Delivery Bucket | W4: Data Quality Flag
A5: 56623 | B5: 45658 | C5: 13 | D5: NSW | E5: Consumer | F5: Connor Betts | G5: Office Supplies | H5: Not Specified | I5: Apex Box Cutter Scissors | J5: 4.19 | K5: 10.23 | L5: 6.04 | M5: 45 | N5: 460.35 | O5: 0.08 | P5: 36.828 | Q5: 423.522 | R5: =TEXT(B5,"mmm") -> Jan | S5: =J5*M5 -> 188.55 | T5: =Q5-S5 -> 234.972 | U5: =IF(Q5=0,0,T5/Q5) -> 0.55480471 | V5: =IF(C5<=3,"Fast",IF(C5<=7,"Standard",IF(C5<=14,"Slow","Very Slow"))) -> Slow | W5: =IF(OR(H5="Not Specifiedd",P5<0),"Review","OK") -> OK
A6: 56624 | B6: 45658 | C6: 6 | D6: WA | E6: Consumer | F6: Yvette Biti | G6: Office Supplies | H6: Critical | I6: Smiths Pushpins | J6: 0.94 | K6: 1.88 | L6: 0.94 | M6: 36 | N6: 67.68 | O6: 0.1 | P6: -6.77 | Q6: 74.45 | R6: =TEXT(B6,"mmm") -> Jan | S6: =J6*M6 -> 33.84 | T6: =Q6-S6 -> 40.61 | U6: =IF(Q6=0,0,T6/Q6) -> 0.54546676 | V6: =IF(C6<=3,"Fast",IF(C6<=7,"Standard",IF(C6<=14,"Slow","Very Slow"))) -> Standard | W6: =IF(OR(H6="Not Specifiedd",P6<0),"Review","OK") -> Review
A7: 56625 | B7: 45659 | C7: 3 | D7: NSW | E7: Small Business | F7: Yvette Biti | G7: Office Supplies | H7: Medium | I7: Artisan Durable Poly Binders | J7: 3.37 | K7: 5.53 | L7: 2.16 | M7: 21 | N7: 116.13 | O7: 0.02 | P7: 2.3226 | Q7: 113.8074 | R7: =TEXT(B7,"mmm") -> Jan | S7: =J7*M7 -> 70.77 | T7: =Q7-S7 -> 43.0374 | U7: =IF(Q7=0,0,T7/Q7) -> 0.37815994 | V7: =IF(C7<=3,"Fast",IF(C7<=7,"Standard",IF(C7<=14,"Slow","Very Slow"))) -> Fast | W7: =IF(OR(H7="Not Specifiedd",P7<0),"Review","OK") -> OK
A8: 56626 | B8: 45661 | C8: 15 | D8: NSW | E8: Consumer | F8: Yvette Biti | G8: Office Supplies | H8: Low | I8: Smiths Bulk Pack Metal Binder Clips | J8: 3.95 | K8: 6.08 | L8: 2.13 | M8: 48 | N8: 291.84 | O8: 0.03 | P8: 8.7552 | Q8: 283.0848 | R8: =TEXT(B8,"mmm") -> Jan | S8: =J8*M8 -> 189.6 | T8: =Q8-S8 -> 93.4848 | U8: =IF(Q8=0,0,T8/Q8) -> 0.33023603 | V8: =IF(C8<=3,"Fast",IF(C8<=7,"Standard",IF(C8<=14,"Slow","Very Slow"))) -> Very Slow | W8: =IF(OR(H8="Not Specifiedd",P8<0),"Review","OK") -> OK
A9: 56627 | B9: 45662 | C9: 4 | D9: NSW | E9: Corporate | F9: Tina Carlton | G9: Office Supplies | H9: Critical | I9: Smiths Pen Style Liquid Stix; Assorted (yellow, pink, green, blue, orange), 5/Pack | J9: 3.88 | K9: 6.47 | L9: 2.59 | M9: 18 | N9: 116.46 | O9: 0.04 | P9: 4.6584 | Q9: 111.8016 | R9: =TEXT(B9,"mmm") -> Jan | S9: =J9*M9 -> 69.84 | T9: =Q9-S9 -> 41.9616 | U9: =IF(Q9=0,0,T9/Q9) -> 0.375322 | V9: =IF(C9<=3,"Fast",IF(C9<=7,"Standard",IF(C9<=14,"Slow","Very Slow"))) -> Standard | W9: =IF(OR(H9="Not Specifiedd",P9<0),"Review","OK") -> OK
A10: 56628 | B10: 45662 | C10: 12 | D10: WA | E10: Corporate | F10: Phoebe Gour | G10: Office Supplies | H10: Not Specifiedd | I10: Xit Blank Computer Paper | J10: 12.39 | K10: 19.98 | L10: 7.59 | M10: 45 | N10: 899.1 | O10: 0.04 | P10: 35.964 | Q10: 863.136 | R10: =TEXT(B10,"mmm") -> Jan | S10: =J10*M10 -> 557.55 | T10: =Q10-S10 -> 305.586 | U10: =IF(Q10=0,0,T10/Q10) -> 0.35404154 | V10: =IF(C10<=3,"Fast",IF(C10<=7,"Standard",IF(C10<=14,"Slow","Very Slow"))) -> Slow | W10: =IF(OR(H10="Not Specifiedd",P10<0),"Review","OK") -> Review
A11: 56629 | B11: 45663 | C11: 7 | D11: NSW | E11: Consumer | F11: Phoebe Gour | G11: Office Supplies | H11: Critical | I11: Apex Box Cutter Scissors | J11: 4.19 | K11: 10.23 | L11: 6.04 | M11: 16 | N11: 163.68 | O11: 0.02 | P11: 3.2736 | Q11: 160.4064 | R11: =TEXT(B11,"mmm") -> Jan | S11: =J11*M11 -> 67.04 | T11: =Q11-S11 -> 93.3664 | U11: =IF(Q11=0,0,T11/Q11) -> 0.58206156 | V11: =IF(C11<=3,"Fast",IF(C11<=7,"Standard",IF(C11<=14,"Slow","Very Slow"))) -> Standard | W11: =IF(OR(H11="Not Specifiedd",P11<0),"Review","OK") -> OK
A12: 56630 | B12: 45663 | C12: 1 | D12: VIC | E12: Small Business | F12: Natasha Song | G12: Office Supplies | H12: Low | I12: Beekin 6 Outlet Metallic Surge Strip | J12: 4.46 | K12: 10.89 | L12: 6.43 | M12: 10 | N12: 108.9 | O12: 0.1 | P12: 10.89 | Q12: 98.01 | R12: =TEXT(B12,"mmm") -> Jan | S12: =J12*M12 -> 44.6 | T12: =Q12-S12 -> 53.41 | U12: =IF(Q12=0,0,T12/Q12) -> 0.54494439 | V12: =IF(C12<=3,"Fast",IF(C12<=7,"Standard",IF(C12<=14,"Slow","Very Slow"))) -> Fast | W12: =IF(OR(H12="Not Specifiedd",P12<0),"Review","OK") -> OK
A13: 56631 | B13: 45663 | C13: 3 | D13: WA | E13: Corporate | F13: Phoebe Gour | G13: Technology | H13: Not Specified | I13: 300 Series Non-Flip | J13: 62.4 | K13: 155.99 | L13: 93.59 | M13: 5 | N13: 779.95 | O13: 0.02 | P13: 15.599 | Q13: 764.351 | R13: =TEXT(B13,"mmm") -> Jan | S13: =J13*M13 -> 312 | T13: =Q13-S13 -> 452.351 | U13: =IF(Q13=0,0,T13/Q13) -> 0.59181057 | V13: =IF(C13<=3,"Fast",IF(C13<=7,"Standard",IF(C13<=14,"Slow","Very Slow"))) -> Fast | W13: =IF(OR(H13="Not Specifiedd",P13<0),"Review","OK") -> OK
A14: 56632 | B14: 45663 | C14: 4 | D14: NSW | E14: Consumer | F14: Radhya Staples | G14: Office Supplies | H14: Low | I14: Beekin 6 Outlet Metallic Surge Strip | J14: 4.46 | K14: 10.89 | L14: 6.43 | M14: 9 | N14: 98.01 | O14: 0.09 | P14: 8.8209 | Q14: 89.1891 | R14: =TEXT(B14,"mmm") -> Jan | S14: =J14*M14 -> 40.14 | T14: =Q14-S14 -> 49.0491 | U14: =IF(Q14=0,0,T14/Q14) -> 0.549945 | V14: =IF(C14<=3,"Fast",IF(C14<=7,"Standard",IF(C14<=14,"Slow","Very Slow"))) -> Standard | W14: =IF(OR(H14="Not Specifiedd",P14<0),"Review","OK") -> OK
A15: 56633 | B15: 45663 | C15: 5 | D15: NSW | E15: Corporate | F15: Leighton Forrest | G15: Furniture | H15: Not Specified | I15: Aluminum Document Frame | J15: 5.5 | K15: 12.22 | L15: 6.72 | M15: 23 | N15: 281.06 | O15: 0.07 | P15: 19.6742 | Q15: 261.3858 | R15: =TEXT(B15,"mmm") -> Jan | S15: =J15*M15 -> 126.5 | T15: =Q15-S15 -> 134.8858 | U15: =IF(Q15=0,0,T15/Q15) -> 0.51604104 | V15: =IF(C15<=3,"Fast",IF(C15<=7,"Standard",IF(C15<=14,"Slow","Very Slow"))) -> Standard | W15: =IF(OR(H15="Not Specifiedd",P15<0),"Review","OK") -> OK
A16: 56634 | B16: 45663 | C16: 16 | D16: NSW | E16: Home Office | F16: Preston Senome | G16: Office Supplies | H16: Critical | I16: Pizazz Colored Pencils | J16: 1.76 | K16: 2.94 | L16: 1.18 | M16: 20 | N16: 58.8 | O16: 0.07 | P16: 4.116 | Q16: 54.684 | R16: =TEXT(B16,"mmm") -> Jan | S16: =J16*M16 -> 35.2 | T16: =Q16-S16 -> 19.484 | U16: =IF(Q16=0,0,T16/Q16) -> 0.35630166 | V16: =IF(C16<=3,"Fast",IF(C16<=7,"Standard",IF(C16<=14,"Slow","Very Slow"))) -> Very Slow | W16: =IF(OR(H16="Not Specifiedd",P16<0),"Review","OK") -> OK
... A783: 57401 | B783: 46022 | C783: 3 | D783: NSW | E783: Home Office | F783: Leighton Forrest | G783: Technology | H783: High | I783: HFX LaserJet 3310 Copier | J783: 377.99 | K783: 599.99 | L783: 222 | M783: 22 | N783: 13199.78 | O783: 0.07 | P783: 923.9846 | Q783: 12275.795 | R783: =TEXT(B783,"mmm") -> Dec | S783: =J783*M783 -> 8315.78 | T783: =Q783-S783 -> 3960.0154 | U783: =IF(Q783=0,0,T783/Q783) -> 0.32258728 | V783: =IF(C783<=3,"Fast",IF(C783<=7,"Standard",IF(C783<=14,"Slow","Very Slow"))) -> Fast | W783: =IF(OR(H783="Not Specifiedd",P783<0),"Review","OK") -> OK

Sheet Salesperson Analysis
A1: Salesperson Performance
A2: Revenue, order volume, units, average order value and gross profit by salesperson.
A4: Salesperson | B4: Orders | C4: Revenue | D4: Units Sold | E4: Avg Order Value | F4: Gross Profit | G4: Rank
A5: Yvette Biti | B5: =COUNTIF(Orders_Clean!$F$2:$F$780,'Salesperson Analysis'!A5) -> 104 | C5: =SUMIF(Orders_Clean!$F$2:$F$780,A5,Orders_Clean!$Q$2:$Q$780) -> 120963.36 | D5: =SUMIF(Orders_Clean!$F$2:$F$780,A5,Orders_Clean!$M$2:$M$780) -> 2930 | E5: =IFERROR('Salesperson Analysis'!C5/'Salesperson Analysis'!B5,0) -> 1163.1092 | F5: =SUMIF(Orders_Clean!$F$5:$F$783,A5,Orders_Clean!$T$5:$T$783) -> 52755.725 | G5: =RANK(F5,$F$5:$F$17,0) -> 1
A6: Natasha Song | B6: =COUNTIF(Orders_Clean!$F$2:$F$780,'Salesperson Analysis'!A6) -> 52 | C6: =SUMIF(Orders_Clean!$F$2:$F$780,A6,Orders_Clean!$Q$2:$Q$780) -> 105627.71 | D6: =SUMIF(Orders_Clean!$F$2:$F$780,A6,Orders_Clean!$M$2:$M$780) -> 1339 | E6: =IFERROR('Salesperson Analysis'!C6/'Salesperson Analysis'!B6,0) -> 2031.302 | F6: =SUMIF(Orders_Clean!$F$5:$F$783,A6,Orders_Clean!$T$5:$T$783) -> 38432.816 | G6: =RANK(E6,$E$5:$E$17,0) -> 2
A7: Tina Carlton | B7: =COUNTIF(Orders_Clean!$F$2:$F$780,'Salesperson Analysis'!A7) -> 112 | C7: =SUMIF(Orders_Clean!$F$2:$F$780,A7,Orders_Clean!$Q$2:$Q$780) -> 95586.719 | D7: =SUMIF(Orders_Clean!$F$2:$F$780,A7,Orders_Clean!$M$2:$M$780) -> 2970 | E7: =IFERROR('Salesperson Analysis'!C7/'Salesperson Analysis'!B7,0) -> 853.45285 | F7: =SUMIF(Orders_Clean!$F$5:$F$783,A7,Orders_Clean!$T$5:$T$783) -> 46112.13 | G7: =RANK(E7,$E$5:$E$17,0) -> 10
A8: Connor Betts | B8: =COUNTIF(Orders_Clean!$F$2:$F$780,'Salesperson Analysis'!A8) -> 110 | C8: =SUMIF(Orders_Clean!$F$2:$F$780,A8,Orders_Clean!$Q$2:$Q$780) -> 88272.502 | D8: =SUMIF(Orders_Clean!$F$2:$F$780,A8,Orders_Clean!$M$2:$M$780) -> 3053 | E8: =IFERROR('Salesperson Analysis'!C8/'Salesperson Analysis'!B8,0) -> 802.47729 | F8: =SUMIF(Orders_Clean!$F$5:$F$783,A8,Orders_Clean!$T$5:$T$783) -> 34289.162 | G8: =RANK(E8,$E$5:$E$17,0) -> 12
A9: Mihael Khan | B9: =COUNTIF(Orders_Clean!$F$2:$F$780,'Salesperson Analysis'!A9) -> 55 | C9: =SUMIF(Orders_Clean!$F$2:$F$780,A9,Orders_Clean!$Q$2:$Q$780) -> 76239.295 | D9: =SUMIF(Orders_Clean!$F$2:$F$780,A9,Orders_Clean!$M$2:$M$780) -> 1584 | E9: =IFERROR('Salesperson Analysis'!C9/'Salesperson Analysis'!B9,0) -> 1386.169 | F9: =SUMIF(Orders_Clean!$F$5:$F$783,A9,Orders_Clean!$T$5:$T$783) -> 28900.905 | G9: =RANK(E9,$E$5:$E$17,0) -> 4
A10: Charlie Bui | B10: =COUNTIF(Orders_Clean!$F$2:$F$780,'Salesperson Analysis'!A10) -> 38 | C10: =SUMIF(Orders_Clean!$F$2:$F$780,A10,Orders_Clean!$Q$2:$Q$780) -> 74020.828 | D10: =SUMIF(Orders_Clean!$F$2:$F$780,A10,Orders_Clean!$M$2:$M$780) -> 862 | E10: =IFERROR('Salesperson Analysis'!C10/'Salesperson Analysis'!B10,0) -> 1947.9165 | F10: =SUMIF(Orders_Clean!$F$5:$F$783,A10,Orders_Clean!$T$5:$T$783) -> 33653.858 | G10: =RANK(E10,$E$5:$E$17,0) -> 3
A11: Radhya Staples | B11: =COUNTIF(Orders_Clean!$F$2:$F$780,'Salesperson Analysis'!A11) -> 13 | C11: =SUMIF(Orders_Clean!$F$2:$F$780,A11,Orders_Clean!$Q$2:$Q$780) -> 72880.071 | D11: =SUMIF(Orders_Clean!$F$2:$F$780,A11,Orders_Clean!$M$2:$M$780) -> 396 | E11: =IFERROR('Salesperson Analysis'!C11/'Salesperson Analysis'!B11,0) -> 5606.1593 | F11: =SUMIF(Orders_Clean!$F$5:$F$783,A11,Orders_Clean!$T$5:$T$783) -> 28524.561 | G11: =RANK(E11,$E$5:$E$17,0) -> 1
A12: Samantha Chairs | B12: =COUNTIF(Orders_Clean!$F$2:$F$780,'Salesperson Analysis'!A12) -> 50 | C12: =SUMIF(Orders_Clean!$F$2:$F$780,A12,Orders_Clean!$Q$2:$Q$780) -> 65786.384 | D12: =SUMIF(Orders_Clean!$F$2:$F$780,A12,Orders_Clean!$M$2:$M$780) -> 1550 | E12: =IFERROR('Salesperson Analysis'!C12/'Salesperson Analysis'!B12,0) -> 1315.7277 | F12: =SUMIF(Orders_Clean!$F$5:$F$783,A12,Orders_Clean!$T$5:$T$783) -> 26500.604 | G12: =RANK(E12,$E$5:$E$17,0) -> 5
A13: Leighton Forrest | B13: =COUNTIF(Orders_Clean!$F$2:$F$780,'Salesperson Analysis'!A13) -> 44 | C13: =SUMIF(Orders_Clean!$F$2:$F$780,A13,Orders_Clean!$Q$2:$Q$780) -> 51399.285 | D13: =SUMIF(Orders_Clean!$F$2:$F$780,A13,Orders_Clean!$M$2:$M$780) -> 937 | E13: =IFERROR('Salesperson Analysis'!C13/'Salesperson Analysis'!B13,0) -> 1168.1656 | F13: =SUMIF(Orders_Clean!$F$5:$F$783,A13,Orders_Clean!$T$5:$T$783) -> 24504.321 | G13: =RANK(E13,$E$5:$E$17,0) -> 7
A14: Phoebe Gour | B14: =COUNTIF(Orders_Clean!$F$2:$F$780,'Salesperson Analysis'!A14) -> 70 | C14: =SUMIF(Orders_Clean!$F$2:$F$780,A14,Orders_Clean!$Q$2:$Q$780) -> 57438.97 | D14: =SUMIF(Orders_Clean!$F$2:$F$780,A14,Orders_Clean!$M$2:$M$780) -> 1891 | E14: =IFERROR('Salesperson Analysis'!C14/'Salesperson Analysis'!B14,0) -> 820.55671 | F14: =SUMIF(Orders_Clean!$F$5:$F$783,A14,Orders_Clean!$T$5:$T$783) -> 28291.76 | G14: =RANK(E14,$E$5:$E$17,0) -> 11
A15: Aanya Zhang | B15: =COUNTIF(Orders_Clean!$F$2:$F$780,'Salesperson Analysis'!A15) -> 52 | C15: =SUMIF(Orders_Clean!$F$2:$F$780,A15,Orders_Clean!$Q$2:$Q$780) -> 55961.527 | D15: =SUMIF(Orders_Clean!$F$2:$F$780,A15,Orders_Clean!$M$2:$M$780) -> 1319 | E15: =IFERROR('Salesperson Analysis'!C15/'Salesperson Analysis'!B15,0) -> 1076.1832 | F15: =SUMIF(Orders_Clean!$F$5:$F$783,A15,Orders_Clean!$T$5:$T$783) -> 31625.817 | G15: =RANK(E15,$E$5:$E$17,0) -> 9
A16: Nicholas Fernandes | B16: =COUNTIF(Orders_Clean!$F$2:$F$780,'Salesperson Analysis'!A16) -> 42 | C16: =SUMIF(Orders_Clean!$F$2:$F$780,A16,Orders_Clean!$Q$2:$Q$780) -> 52944.984 | D16: =SUMIF(Orders_Clean!$F$2:$F$780,A16,Orders_Clean!$M$2:$M$780) -> 980 | E16: =IFERROR('Salesperson Analysis'!C16/'Salesperson Analysis'!B16,0) -> 1260.5948 | F16: =SUMIF(Orders_Clean!$F$5:$F$783,A16,Orders_Clean!$T$5:$T$783) -> 24229.476 | G16: =RANK(E16,$E$5:$E$17,0) -> 6
A17: Preston Senome | B17: =COUNTIF(Orders_Clean!$F$2:$F$780,'Salesperson Analysis'!A17) -> 34 | C17: =SUMIF(Orders_Clean!$F$2:$F$780,A17,Orders_Clean!$Q$2:$Q$780) -> 16016.52 | D17: =SUMIF(Orders_Clean!$F$2:$F$780,A17,Orders_Clean!$M$2:$M$780) -> 963 | E17: =IFERROR('Salesperson Analysis'!C17/'Salesperson Analysis'!B17,0) -> 471.0741 | F17: =SUMIF(Orders_Clean!$F$5:$F$783,A17,Orders_Clean!$T$5:$T$783) -> 6978.2143 | G17: =RANK(E17,$E$5:$E$17,0) -> 13

Sheet Customer Analysis
A1: Customer Segment Analysis
A2: Revenue and order contribution by customer type.
A4: Customer Type | B4: Orders | C4: Revenue | D4: Units Sold | E4: Avg Order Value | F4: Profit
A5: Consumer | B5: =COUNTIF(Orders_Clean!$E$5:$E$783,A5) -> 140 | C5: =SUMIF(Orders_Clean!$E$5:$E$783,A5,Orders_Clean!$Q$5:$Q$783) -> 167363.3 | D5: =SUMIF(Orders_Clean!$E$5:$E$783,A5,Orders_Clean!$N$5:$N$783) -> 176445.35 | E5: =IF(B5=0,0,C5/B5) -> 1195.4521 | F5: =SUMIF('Customer Analysis'!$A$5:$A$8,'Customer Analysis'!A5,Orders_Clean!$U$758:$U$783) -> 0.35815148
A6: Corporate | B6: =COUNTIF(Orders_Clean!$E$5:$E$783,A6) -> 275 | C6: =SUMIF(Orders_Clean!$E$5:$E$783,A6,Orders_Clean!$Q$5:$Q$783) -> 369291.8 | D6: =SUMIF(Orders_Clean!$E$5:$E$783,A6,Orders_Clean!$N$5:$N$783) -> 392865.08 | E6: =IF(B6=0,0,C6/B6) -> 1342.8793 | F6: =SUMIF('Customer Analysis'!$A$5:$A$8,'Customer Analysis'!A6,Orders_Clean!$U$758:$U$783) -> 0.39673886
A7: Home Office | B7: =COUNTIF(Orders_Clean!$E$5:$E$783,A7) -> 203 | C7: =SUMIF(Orders_Clean!$E$5:$E$783,A7,Orders_Clean!$Q$5:$Q$783) -> 220046.86 | D7: =SUMIF(Orders_Clean!$E$5:$E$783,A7,Orders_Clean!$N$5:$N$783) -> 234916.9 | E7: =IF(B7=0,0,C7/B7) -> 1083.9747 | F7: =SUMIF('Customer Analysis'!$A$5:$A$8,'Customer Analysis'!A7,Orders_Clean!$U$758:$U$783) -> 0.50396825
A8: Small Business | B8: =COUNTIF(Orders_Clean!$E$5:$E$783,A8) -> 161 | C8: =SUMIF(Orders_Clean!$E$5:$E$783,A8,Orders_Clean!$Q$5:$Q$783) -> 189467.84 | D8: =SUMIF(Orders_Clean!$E$5:$E$783,A8,Orders_Clean!$N$5:$N$783) -> 198167.63 | E8: =IF(B8=0,0,C8/B8) -> 1176.8189 | F8: =SUMIF('Customer Analysis'!$A$5:$A$8,'Customer Analysis'!A8,Orders_Clean!$U$758:$U$783) -> 0.34733834

Sheet State Analysis
A1: State / Territory Performance
A2: Geographic revenue and volume reporting.
A4: State | B4: Orders | C4: Revenue | D4: Units Sold | E4: Avg Order Value
A5: NSW | B5: =COUNTIF(Orders_Clean!$D$5:$D$783,A5) -> 447 | C5: =SUMIF(Orders_Clean!$D$5:$D$783,A5,Orders_Clean!$Q$5:$Q$783) -> 578438.14 | D5: =SUMIF(Orders_Clean!$D$5:$D$783,A5,Orders_Clean!$M$5:$M$783) -> 11711 | E5: =IF(B5=0,0,C5/B5) -> 1294.0451
A6: VIC | B6: =COUNTIF(Orders_Clean!$D$5:$D$783,A6) -> 184 | C6: =SUMIF(Orders_Clean!$D$5:$D$783,A6,Orders_Clean!$Q$5:$Q$783) -> 210288.43 | D6: =SUMIF(Orders_Clean!$D$5:$D$783,A6,Orders_Clean!$M$5:$M$783) -> 4943 | E6: =IF(B6=0,0,C6/B6) -> 1142.8719
A7: WA | B7: =COUNTIF(Orders_Clean!$D$5:$D$783,A7) -> 148 | C7: =SUMIF(Orders_Clean!$D$5:$D$783,A7,Orders_Clean!$Q$5:$Q$783) -> 157443.23 | D7: =SUMIF(Orders_Clean!$D$5:$D$783,A7,Orders_Clean!$M$5:$M$783) -> 4206 | E7: =IF(B7=0,0,C7/B7) -> 1063.8056

Sheet Category Analysis
A1: Product Category Performance
A2: Unit sales, revenue and gross profit by category.
A4: Product Category | B4: Units Sold | C4: Revenue | D4: Gross Profit
A5: Furniture | B5: =SUMIF(Orders_Clean!$G$5:$G$783,A5,Orders_Clean!$M$5:$M$783) -> 478 | C5: =SUMIF(Orders_Clean!$G$5:$G$783,A5,Orders_Clean!$Q$5:$Q$783) -> 24961.874 | D5: =SUMIF(Orders_Clean!$G$5:$G$783,A5,Orders_Clean!$T$5:$T$783) -> 13651.034
A6: Office Supplies | B6: =SUMIF(Orders_Clean!$G$5:$G$783,A6,Orders_Clean!$M$5:$M$783) -> 16669 | C6: =SUMIF(Orders_Clean!$G$5:$G$783,A6,Orders_Clean!$Q$5:$Q$783) -> 266028.18 | D6: =SUMIF(Orders_Clean!$G$5:$G$783,A6,Orders_Clean!$T$5:$T$783) -> 119488.44
A7: Technology | B7: =SUMIF(Orders_Clean!$G$5:$G$783,A7,Orders_Clean!$M$5:$M$783) -> 3713 | C7: =SUMIF(Orders_Clean!$G$5:$G$783,A7,Orders_Clean!$Q$5:$Q$783) -> 655179.74 | D7: =SUMIF(Orders_Clean!$G$5:$G$783,A7,Orders_Clean!$T$5:$T$783) -> 271659.87

Sheet Monthly Analysis
A1: Monthly Revenue Trend
A2: Monthly reporting for trend analysis and management reporting.
A4: Month | B4: Orders | C4: Revenue | D4: Gross Profit
A5: Jan | B5: =COUNTIF(Orders_Clean!$R$5:$R$783,A5) -> 65 | C5: =SUMIF(Orders_Clean!$R$5:$R$783,A5,Orders_Clean!$Q$5:$Q$783) -> 56974.562 | D5: =SUMIF(Orders_Clean!$R$5:$R$783,A5,Orders_Clean!$T$5:$T$783) -> 28096.872
A6: Feb | B6: =COUNTIF(Orders_Clean!$R$5:$R$783,A6) -> 53 | C6: =SUMIF(Orders_Clean!$R$5:$R$783,A6,Orders_Clean!$Q$5:$Q$783) -> 58662.096 | D6: =SUMIF(Orders_Clean!$R$5:$R$783,A6,Orders_Clean!$T$5:$T$783) -> 28564.576
A7: Mar | B7: =COUNTIF(Orders_Clean!$R$5:$R$783,A7) -> 75 | C7: =SUMIF(Orders_Clean!$R$5:$R$783,A7,Orders_Clean!$Q$5:$Q$783) -> 143970.12 | D7: =SUMIF(Orders_Clean!$R$5:$R$783,A7,Orders_Clean!$T$5:$T$783) -> 56520.558
A8: Apr | B8: =COUNTIF(Orders_Clean!$R$5:$R$783,A8) -> 58 | C8: =SUMIF(Orders_Clean!$R$5:$R$783,A8,Orders_Clean!$Q$5:$Q$783) -> 54408.572 | D8: =SUMIF(Orders_Clean!$R$5:$R$783,A8,Orders_Clean!$T$5:$T$783) -> 23119.222
A9: May | B9: =COUNTIF(Orders_Clean!$R$5:$R$783,A9) -> 66 | C9: =SUMIF(Orders_Clean!$R$5:$R$783,A9,Orders_Clean!$Q$5:$Q$783) -> 87835.631 | D9: =SUMIF(Orders_Clean!$R$5:$R$783,A9,Orders_Clean!$T$5:$T$783) -> 35691.981
A10: Jun | B10: =COUNTIF(Orders_Clean!$R$5:$R$783,A10) -> 61 | C10: =SUMIF(Orders_Clean!$R$5:$R$783,A10,Orders_Clean!$Q$5:$Q$783) -> 93178.52 | D10: =SUMIF(Orders_Clean!$R$5:$R$783,A10,Orders_Clean!$T$5:$T$783) -> 35740.99
A11: Jul | B11: =COUNTIF(Orders_Clean!$R$5:$R$783,A11) -> 68 | C11: =SUMIF(Orders_Clean!$R$5:$R$783,A11,Orders_Clean!$Q$5:$Q$783) -> 105093.69 | D11: =SUMIF(Orders_Clean!$R$5:$R$783,A11,Orders_Clean!$T$5:$T$783) -> 44949.256
A12: Aug | B12: =COUNTIF(Orders_Clean!$R$5:$R$783,A12) -> 67 | C12: =SUMIF(Orders_Clean!$R$5:$R$783,A12,Orders_Clean!$Q$5:$Q$783) -> 43467.029 | D12: =SUMIF(Orders_Clean!$R$5:$R$783,A12,Orders_Clean!$T$5:$T$783) -> 21362.229
A13: Sep | B13: =COUNTIF(Orders_Clean!$R$5:$R$783,A13) -> 65 | C13: =SUMIF(Orders_Clean!$R$5:$R$783,A13,Orders_Clean!$Q$5:$Q$783) -> 73635.172 | D13: =SUMIF(Orders_Clean!$R$5:$R$783,A13,Orders_Clean!$T$5:$T$783) -> 29101.303
A14: Oct | B14: =COUNTIF(Orders_Clean!$R$5:$R$783,A14) -> 66 | C14: =SUMIF(Orders_Clean!$R$5:$R$783,A14,Orders_Clean!$Q$5:$Q$783) -> 54593.492 | D14: =SUMIF(Orders_Clean!$R$5:$R$783,A14,Orders_Clean!$T$5:$T$783) -> 23033.402
A15: Nov | B15: =COUNTIF(Orders_Clean!$R$5:$R$783,A15) -> 58 | C15: =SUMIF(Orders_Clean!$R$5:$R$783,A15,Orders_Clean!$Q$5:$Q$783) -> 59446.994 | D15: =SUMIF(Orders_Clean!$R$5:$R$783,A15,Orders_Clean!$T$5:$T$783) -> 30447.414
A16: Dec | B16: =COUNTIF(Orders_Clean!$R$5:$R$783,A16) -> 77 | C16: =SUMIF(Orders_Clean!$R$5:$R$783,A16,Orders_Clean!$Q$5:$Q$783) -> 114903.93 | D16: =SUMIF(Orders_Clean!$R$5:$R$783,A16,Orders_Clean!$T$5:$T$783) -> 48171.546

Sheet Delivery Analysis
A1: Delivery Performance
A2: Uses Days to Deliver to create operational reporting buckets.
A4: Delivery Bucket | B4: Orders | C4: Avg Days to Deliver | D4: Revenue | E4: Gross Profit
A5: Fast | B5: =COUNTIF(Orders_Clean!$V$5:$V$980,A5) -> 101 | C5: =AVERAGEIF(Orders_Clean!$V$5:$V$980,A5,Orders_Clean!$C$5:$C$980) -> 2.0693069 | D5: =SUMIF(Orders_Clean!$V$5:$V$980,A5,Orders_Clean!$Q$5:$Q$980) -> 130997.38 | E5: =SUMIF(Orders_Clean!$V$5:$V$783,A5,Orders_Clean!$T$5:$T$783) -> 50414.544
A6: Standard | B6: =COUNTIF(Orders_Clean!$V$5:$V$980,A6) -> 137 | C6: =AVERAGEIF(Orders_Clean!$V$5:$V$980,A6,Orders_Clean!$C$5:$C$980) -> 5.5985401 | D6: =SUMIF(Orders_Clean!$V$5:$V$980,A6,Orders_Clean!$Q$5:$Q$980) -> 90110.98 | E6: =SUMIF(Orders_Clean!$V$5:$V$783,A6,Orders_Clean!$T$5:$T$783) -> 42165.93
A7: Slow | B7: =COUNTIF(Orders_Clean!$V$5:$V$980,A7) -> 247 | C7: =AVERAGEIF(Orders_Clean!$V$5:$V$980,A7,Orders_Clean!$C$5:$C$980) -> 10.927126 | D7: =SUMIF(Orders_Clean!$V$5:$V$980,A7,Orders_Clean!$Q$5:$Q$980) -> 308364.38 | E7: =SUMIF(Orders_Clean!$V$5:$V$783,A7,Orders_Clean!$T$5:$T$783) -> 131348.66
A8: Very Slow | B8: =COUNTIF(Orders_Clean!$V$5:$V$980,A8) -> 294 | C8: =AVERAGEIF(Orders_Clean!$V$5:$V$980,A8,Orders_Clean!$C$5:$C$980) -> 18.663265 | D8: =SUMIF(Orders_Clean!$V$5:$V$980,A8,Orders_Clean!$Q$5:$Q$980) -> 416697.06 | E8: =SUMIF(Orders_Clean!$V$5:$V$783,A8,Orders_Clean!$T$5:$T$783) -> 180870.22

Sheet KPI Summary
A1: KPI Summary
A2: Management-ready KPI calculations using Excel 2010 formulas.
A5: Total Revenue | B5: =SUM(Orders_Clean!$Q$5:$Q$783) -> 946169.8
A6: Total Orders | B6: =COUNTA(Orders_Clean!$A$5:$A$783) -> 779
A7: Units Sold | B7: =SUM(Orders_Clean!$N$5:$N$783) -> 1002395
A8: Gross Cost | B8: =SUM(Orders_Clean!$S$5:$S$783) -> 541370.45
A9: Gross Profit | B9: =SUM(Orders_Clean!$T$5:$T$783) -> 404799.35
A10: Profit Margin % | B10: =IF(B5=0,0,B9/B5) -> 0.4278295
A11: Average Order Value | B11: =IF(B6=0,0,B5/B6) -> 1214.5954
A12: Average Discount % | B12: =AVERAGE(Orders_Clean!$P$5:$P$783) -> 72.176074
A13: Average Days to Deliver | B13: =AVERAGE(Orders_Clean!$C$5:$C$783) -> 11.761232

Sheet Practice Lab
A1: Practice Lab
A2: Use the integrated workbook to practice the same skills covered across the three original projects.
A4: # | B4: Practice Area | C4: Task | D4: Excel Skill
A5: 1 | B5: Basic formula | C5: Calculate total revenue from Orders_Clean using SUM. | D5: SUM
A6: 2 | B6: Conditional calculation | C6: Calculate revenue for Corporate customers using SUMIF. | D6: SUMIF
A7: 3 | B7: Counting | C7: Count orders handled by each salesperson using COUNTIF. | D7: COUNTIF
A8: 4 | B8: Average | C8: Calculate average Days to Deliver by delivery bucket using AVERAGEIF. | D8: AVERAGEIF
A9: 5 | B9: Lookup | C9: Use VLOOKUP or INDEX/MATCH to return a salesperson's revenue from Salesperson Analysis. | D9: VLOOKUP / INDEX-MATCH
A10: 6 | B10: Ranking | C10: Rank salespeople by revenue using RANK. | D10: RANK
A11: 7 | B11: Date analysis | C11: Create Order Month from Order Date using TEXT or MONTH. | D11: TEXT / MONTH
A12: 8 | B12: Profitability | C12: Calculate Gross Cost, Gross Profit and Profit %. | D12: Arithmetic / IF
A13: 9 | B13: Data quality | C13: Identify records where Order Priority is 'Not Specifiedd' or Discount $ is negative. | D13: IF / OR
A14: 10 | B14: Reporting | C14: Create a monthly revenue chart and explain the highest and lowest months. | D14: Charts
A15: 11 | B15: MIS report | C15: Build a one-page management report with Revenue, Orders, Units, AOV, Gross Profit and Delivery KPIs. | D15: Reporting
... A18: 14 | B18: Interview practice | C18: Explain the workbook end-to-end: cleaning → calculations → summaries → dashboard → insights. | D18: Communication

Sheet Portfolio Notes
A1: Portfolio Notes
A2: How to position this workbook for analyst roles.
A4: Project Title | B4: Sales Performance & Revenue Analysis
A5: Tools | B5: Microsoft Excel 2010
A6: Core Skills | B6: Data cleaning, Excel formulas, conditional logic, aggregation, lookup functions, ranking, date analysis, KPI reporting, dashboarding and business insights.
A7: Data Analysis | B7: Revenue by salesperson, customer type, state, product category and month; order volume; units sold; average order value; gross profit; discount analysis; delivery performance.
A8: MIS / Reporting Angle | B8: Recurring KPI reporting, management dashboard, summarized performance tables, exception flags and operational delivery reporting.
A9: Data Analyst Angle | B9: Structured raw data, calculated fields, quality checks, segmentation, trend analysis and actionable insights.
A10: Interview Story | B10: I consolidated three Excel sales-analysis exercises into one end-to-end reporting solution. I kept a single master transaction table to avoid double-counting, added calculated fields for month/profit/delivery, built analysis tables and created a management dashboard.'
A11: LinkedIn/GitHub Description | B11: Built an Excel 2010 Sales Performance & Revenue Analysis project covering transaction-level data preparation, KPI reporting, salesperson performance, customer segmentation, product/category analysis, geographic performance, monthly trends, delivery metrics and an executive dashboard.

Sheet Data Dictionary
A1: Column | B1: Meaning | C1: Type | D1: Business Use
A2: Order Date | B2: Date order was placed | C2: Date | D2: Trend analysis
A3: Salesperson | B3: Person responsible for sale | C3: Dimension | D3: Performance
A4: State | B4: Customer/order state | C4: Dimension | D4: Regional analysis
A5: Customer Type | B5: Customer segment | C5: Dimension | D5: Segmentation
A6: Category | B6: Product category | C6: Dimension | D6: Category analysis
A7: Product | B7: Product sold | C7: Dimension | D7: Product analysis
A8: Quantity | B8: Units sold | C8: Measure | D8: Volume
A9: Cost | B9: Product cost | C9: Measure | D9: Profitability
A10: Retail Price | B10: Selling price | C10: Measure | D10: Revenue
A11: Discount | B11: Discount applied | C11: Measure | D11: Pricing analysis
A12: Revenue | B12: Sales generated | C12: Measure | D12: Revenue KPI
... A14: Delivery Days | B14: Days to deliver | C14: Measure | D14: Operations
